PromptTrack/__init__.py
PromptTrack/detection_utils.py
PromptTrack/mdetr_tracking.py
PromptTrack/utils.py
PromptTrack/tracker/__init__.py
PromptTrack/tracker/basetrack.py
PromptTrack/tracker/byte_tracker.py
PromptTrack/tracker/kalman_filter.py
PromptTrack/tracker/matching.py
PromptTrack-1.0.2.dist-info/METADATA
PromptTrack-1.0.2.dist-info/WHEEL
PromptTrack-1.0.2.dist-info/top_level.txt
PromptTrack-1.0.2.dist-info/RECORD
