Metadata-Version: 2.2
Name: PromptTrack
Version: 1.0.2
Summary: Demo library
Home-page: https://PaquetLab_PromptTrack.readthedocs.io/
Author: sophie NGO BIBINBE
Author-email: anne.ngobibinbe@gmail.com
License: MIT
Classifier: Intended Audience :: Developers
Classifier: License :: OSI Approved :: MIT License
Classifier: Programming Language :: Python
Classifier: Programming Language :: Python :: 3
Classifier: Programming Language :: Python :: 3.9
Classifier: Programming Language :: Python :: 3.10
Classifier: Programming Language :: Python :: 3.11
Classifier: Programming Language :: Python :: 3.12
Classifier: Operating System :: OS Independent
Requires-Dist: numpy
Requires-Dist: timm
Requires-Dist: transformers
Requires-Dist: matplotlib
Requires-Dist: lap
Requires-Dist: scikit-image
Requires-Dist: opencv-python
Requires-Dist: nms
Requires-Dist: torch
Requires-Dist: torchvision
Requires-Dist: torchaudio
Dynamic: author
Dynamic: author-email
Dynamic: classifier
Dynamic: description
Dynamic: description-content-type
Dynamic: home-page
Dynamic: license
Dynamic: requires-dist
Dynamic: summary
